{"expires":1756155381940,"value":{"code":200,"headers":{"etag":"W/\"H3jJjhgYBv\"","last-modified":"Mon, 18 Aug 2025 20:56:23 GMT","cache-control":"s-maxage=604800, stale-while-revalidate"},"body":{"prefix":"icons8","lastModified":1722794108,"aliases":{},"width":32,"height":32,"icons":{"plus":{"body":"<path fill=\"currentColor\" d=\"M16 3C8.832 3 3 8.832 3 16s5.832 13 13 13s13-5.832 13-13S23.168 3 16 3m0 2c6.087 0 11 4.913 11 11s-4.913 11-11 11S5 22.087 5 16S9.913 5 16 5m-1 5v5h-5v2h5v5h2v-5h5v-2h-5v-5z\"/>"}}}},"mtime":1755550583284,"integrity":"maX4dISsQJ"}